vibrant_client/__init__.py
vibrant_client/client.py
vibrant_client/types.py
vibrant_oauth2_client-1.0.0.dist-info/METADATA
vibrant_oauth2_client-1.0.0.dist-info/WHEEL
vibrant_oauth2_client-1.0.0.dist-info/RECORD
