Metadata-Version: 2.4
Name: vibrant-oauth2-client
Version: 1.0.0
Summary: Vibrant OAuth2 Client Library for Python
Project-URL: Homepage, https://github.com/Wang-tianhao/Vibrant-Oauth2-client-python
Project-URL: Repository, https://github.com/Wang-tianhao/Vibrant-Oauth2-client-python
Author: Wang Tianhao
License: MIT
Keywords: authentication,client,oauth2,vibrant
Classifier: Development Status :: 5 - Production/Stable
Classifier: Intended Audience :: Developers
Classifier: License :: OSI Approved :: MIT License
Classifier: Operating System :: OS Independent
Classifier: Programming Language :: Python :: 3
Classifier: Programming Language :: Python :: 3.8
Classifier: Programming Language :: Python :: 3.9
Classifier: Programming Language :: Python :: 3.10
Classifier: Programming Language :: Python :: 3.11
Classifier: Programming Language :: Python :: 3.12
Classifier: Topic :: Software Development :: Libraries :: Python Modules
Requires-Python: >=3.8
Requires-Dist: requests>=2.20.0
